src/__init__.py
src/__main__.py
src/server.py
src/sse_server.py
src/t212.py
mcp_server_trading212-0.2.1.dist-info/METADATA
mcp_server_trading212-0.2.1.dist-info/WHEEL
mcp_server_trading212-0.2.1.dist-info/entry_points.txt
mcp_server_trading212-0.2.1.dist-info/licenses/LICENSE
mcp_server_trading212-0.2.1.dist-info/RECORD
