Metadata-Version: 2.4
Name: mcp-server-trading212
Version: 0.2.1
Summary: This MCP tool will allow AI agents to connect to your Trading212 account in order to manage your portfolio for you
License-File: LICENSE
Requires-Python: >=3.10
Requires-Dist: asyncio>=3.4.3
Requires-Dist: cachetools>=5.5.2
Requires-Dist: click>=8.1.8
Requires-Dist: fuzzywuzzy>=0.18.0
Requires-Dist: httpx>=0.28.1
Requires-Dist: mcp[cli]>=1.7.1
Requires-Dist: python-levenshtein>=0.27.1
Requires-Dist: redis>=6.0.0
